aesara_theano_fallback/__init__.py
aesara_theano_fallback/aesara_theano_fallback_version.py
aesara_theano_fallback/compat.py
aesara_theano_fallback/graph.py
aesara_theano_fallback/tensor.py
aesara_theano_fallback-0.1.0.dist-info/LICENSE
aesara_theano_fallback-0.1.0.dist-info/METADATA
aesara_theano_fallback-0.1.0.dist-info/WHEEL
aesara_theano_fallback-0.1.0.dist-info/top_level.txt
aesara_theano_fallback-0.1.0.dist-info/zip-safe
aesara_theano_fallback-0.1.0.dist-info/RECORD
