Metadata-Version: 2.1
Name: aesara_theano_fallback
Version: 0.1.0
Summary: Striving towards backwards compatibility with the Theano -> Aesara transition
Home-page: https://github.com/exoplanet-dev/aesara-theano-fallback
Author: Dan Foreman-Mackey, Rodrigo Luger
Author-email: foreman.mackey@gmail.com
Maintainer: Dan Foreman-Mackey, Rodrigo Luger
Maintainer-email: foreman.mackey@gmail.com
License: MIT
Platform: UNKNOWN
Classifier: Development Status :: 5 - Production/Stable
Classifier: Intended Audience :: Developers
Classifier: Intended Audience :: Science/Research
Classifier: License :: OSI Approved :: BSD License
Classifier: Operating System :: OS Independent
Classifier: Programming Language :: Python
Classifier: Programming Language :: Python :: 3
Requires-Python: >=3.6
Provides-Extra: test
License-File: LICENSE
